resconfig/__init__.py
resconfig/actions.py
resconfig/clargs.py
resconfig/ondict.py
resconfig/resconfig.py
resconfig/schema.py
resconfig/typing.py
resconfig/utils.py
resconfig/watchers.py
resconfig/io/__init__.py
resconfig/io/ini.py
resconfig/io/io.py
resconfig/io/json.py
resconfig/io/paths.py
resconfig/io/toml.py
resconfig/io/utils.py
resconfig/io/yaml.py
resconfig-20.4.3a0.dist-info/LICENSE.txt
resconfig-20.4.3a0.dist-info/METADATA
resconfig-20.4.3a0.dist-info/WHEEL
resconfig-20.4.3a0.dist-info/entry_points.txt
resconfig-20.4.3a0.dist-info/top_level.txt
resconfig-20.4.3a0.dist-info/RECORD
